Workbook
Name ListeNomsUniques: _xlfn.UNIQUE(ListeNoms!$A$2:$A$120)

Sheet ListeNoms
A1: NOM | B1: Prénom | C1: Numéro | D1: Mail | E1: Proximité | F1: Réseau | G1: Intérêt Invest | H1: Intérêt Métier | I1: Relation | J1: R0 | K1: R1 | L1: R2 | M1: R3 | N1: Webinaire | O1: Présentation métier | P1: JD | Q1: Dans l'équipe
J2: FALSE | K2: FALSE | L2: FALSE | M2: FALSE | N2: FALSE | O2: FALSE | P2: FALSE | Q2: FALSE
J3: FALSE | K3: FALSE | L3: FALSE | M3: FALSE | N3: FALSE | O3: FALSE | P3: FALSE | Q3: FALSE
J4: FALSE | K4: FALSE | L4: FALSE | M4: FALSE | N4: FALSE | O4: FALSE | P4: FALSE | Q4: FALSE
J5: FALSE | K5: FALSE | L5: FALSE | M5: FALSE | N5: FALSE | O5: FALSE | P5: FALSE | Q5: FALSE
J6: FALSE | K6: FALSE | L6: FALSE | M6: FALSE | N6: FALSE | O6: FALSE | P6: FALSE | Q6: FALSE
J7: FALSE | K7: FALSE | L7: FALSE | M7: FALSE | N7: FALSE | O7: FALSE | P7: FALSE | Q7: FALSE
J8: FALSE | K8: FALSE | L8: FALSE | M8: FALSE | N8: FALSE | O8: FALSE | P8: FALSE | Q8: FALSE
J9: FALSE | K9: FALSE | L9: FALSE | M9: FALSE | N9: FALSE | O9: FALSE | P9: FALSE | Q9: FALSE
J10: FALSE | K10: FALSE | L10: FALSE | M10: FALSE | N10: FALSE | O10: FALSE | P10: FALSE | Q10: FALSE
J11: FALSE | K11: FALSE | L11: FALSE | M11: FALSE | N11: FALSE | O11: FALSE | P11: FALSE | Q11: FALSE
J12: FALSE | K12: FALSE | L12: FALSE | M12: FALSE | N12: FALSE | O12: FALSE | P12: FALSE | Q12: FALSE
J13: FALSE | K13: FALSE | L13: FALSE | M13: FALSE | N13: FALSE | O13: FALSE | P13: FALSE | Q13: FALSE
... J183: FALSE | K183: FALSE | L183: FALSE | M183: FALSE | N183: FALSE | O183: FALSE | P183: FALSE | Q183: FALSE

Sheet RoadMap2026
A1: Catégorie | B1: Produit | C1: Action | D1: Quantité visées | E1: Montant mensuel | F1: Montants visés | G1: Quantité réalisée | H1: Montant mensuel réalisé | I1: Montants réalisés
A2: Immo | B2: Résidence principale | C2: Signature projet dans le stock | D2: 1 | F2: 200000
A3: Immo | B3: De Normandie | C3: Signature projet dans le stock | D3: 1 | F3: 150000
A4: Assurance | B4: Assurance Vie | C4: Ouverture de nouveaux contrats | D4: 2 | F4: 1000
A5: Assurance | B5: Assurance Vie | C5: VP | D5: 4 | E5: =50+300+50+50 -> 450 | F5: =12*Tableau13[[#This Row],[Montant mensuel]] -> 5400
A6: Assurance | B6: PER | C6: Ouverture de nouveaux contrats | D6: 2 | F6: 20000
A7: Assurance | B7: PER | C7: VP | D7: 3 | E7: 550 | F7: =12*Tableau13[[#This Row],[Montant mensuel]] -> 6600
A8: Financier | B8: SCPI | C8: Souscription avec crédit | D8: 2 | F8: 200000
A9: Financier | B9: FCPI | C9: Souscription | D9: 2 | F9: 6500
A10: Dev équipe | C10: Recrutement de nouveaux CGP | D10: 2
A11: Total | E11: =SUM(E2:E10) -> 1000 | F11: =SUM(F2:F10) -> 589500 | H11: =SUM(H2:H10) -> 0 | I11: =SUM(I2:I10) -> 0

Sheet Production_2025
A1: Équation du succès Production | J1: Critères | K1: Objectif | L1: Réel
A2: VA = X x Y x Z | J2: VA = Volume d'affaires | K2: =K3*K4*K5 -> 25000 | L2: =SUM(H7:H100) -> 0 | M2: Nouveaux clients :
A3: Année PMR : | J3: X = Nombre de R1 | K3: 5 | L3: =C5 -> 0 | M3: =L3*L4 -> #DIV/0!
A4: Remplir les colonnes R1 et Transformation : 1 si signature ; 0 si pas de suite | J4: Y = Taux de transformation | K4: 0.5 | L4: =E5 -> #DIV/0! | M4: VP :
B5: TOTAUX | C5: =SUM(C7:C100) -> 0 | D5: =SUM(D7:D100) -> 0 | E5: =AVERAGE(E7:E100) -> #DIV/0! | H5: =AVERAGE(H7:H100) -> #DIV/0! | J5: Z = Assiette d'investissement | K5: 10000 | L5: =H5 -> #DIV/0! | M5: =100*E7+300*E8+200*E10+50*E12 -> 0
A6: Nom | B6: Prénom | C6: R1 | D6: R suivi | E6: Transformation | F6: Produit | G6: Remarque | H6: Assiette d'investissement
J7: VA cible | K7: =_xlfn.CONCAT("PV moyen = ",K8) -> PV moyen = 0.4 | L7: =_xlfn.CONCAT("TPC = ",L8*100,"%") -> TPC = 5% | M7: Rémunération brute
J8: =K2 -> 25000 | K8: 0.4 | L8: 0.05 | M8: =J8*K8*L8 -> 500
J9: VA réel | K9: =_xlfn.CONCAT("PV moyen = ",K10) -> PV moyen = 0.4 | L9: =_xlfn.CONCAT("TPC = ",L10*100,"%") -> TPC = 5% | M9: Rémunération brute
J10: =L2 -> 0 | K10: 0.4 | L10: =L8 -> 0.05 | M10: =J10*K10*L10 -> 0
J12: Notes pour vous aider dans vos simulations :
J13: Nombre de R1 : pour un démarrage réussi, on table sur 40 R1 la première année, soit environ 1 par semaine.
J14: Taux de transformation : 50% pour un débutant seul.
J15: Si vous êtes accompagné d'un Manager Upline, le taux monte pour se rapprocher de 90%
J16: Assiette d'investissement : environ 15 000€ par investisseur pour un débutant
J18: Rappel des points valeurs sur les investissements :
J19: Assurance vie / PER / contrats de capitalisation : 0,4 (à 4,80% de droits d'entrée)
J20: SCPI : 0,4 (0,5 si vous êtes CIF) | L20: PV moyen : 0,5
J21: Capital Investissement : 0,4
J22: Girardin : entre 0,27 et 0,3
J23: Immo : entre 0,3 et 0,8
J24: Prévoyance : 1,2
J26: Taux Personnel de Commission :
J27: Consultant Junior : 3%
J28: Consultant habilité : 5%
J29: Manager : 6%
J30: Manager Planète : 6,5%
J31: Manager Étoile : 7% | L31: Major (> 1 million d'€ de VA : 7%)
J32: Manager Constellation : 7,5%
J33: Manager Galaxie : 8% | L33: Expert (> 1,5 million d'€ de VA : 8%)

Sheet Développement
A1: Équation du succès Développement | H1: Critères | I1: Objectif | J1: Réel
A2: S' = X' x Y' x Z' | H2: S' = Filleul lancé | I2: =I3*I4*I5 -> 1 | J2: =E29 -> 0
A3: Année PMR : | H3: X' = Nombre POA | I3: 10 | J3: =C29 -> 0
A4: Remplir les colonnes POA , Convention et 1er contrat : 1 ou 0 | H4: Y' = Taux conventions | I4: 0.2 | J4: =D29 -> 0
A5: Prénom | B5: NOM | C5: POA | D5: Convention | E5: 1er contrat | H5: Z' = Taux de premier contrat | I5: 0.5 | J5: =E29 -> 0
C6: 0 | D6: 0 | E6: 0
C7: 0 | D7: 0 | E7: 0 | H7: Notes pour vous aider dans vos simulations :
C8: 0 | D8: 0 | E8: 0 | H8: Statistique réseau : 1 parrainage tous les 18 mois
C9: 0 | D9: 0 | E9: 0 | H9: Objectif pour une duplication éfficace : 2 parrainages (filleuls lancés) par an à titre perso + 2 parrainages par an par membres de l'équipe
C10: 0 | D10: 0 | E10: 0
C11: 0 | D11: 0 | E11: 0
C12: 0 | D12: 0 | E12: 0 | H12: Projections : | I12: Parrainages perso | J12: Directs | K12: Total équipe
C13: 0 | D13: 0 | E13: 0 | H13: Année 1 : | I13: =I2 -> 1 | J13: =I2 -> 1 | K13: =J13+1 -> 2
C14: 0 | D14: 0 | E14: 0 | H14: Année 2 : | I14: =I2 -> 1 | J14: =J13+I14 -> 2 | K14: =(J14+(K13-1)*2)+1 -> 5
C15: 0 | D15: 0 | E15: 0 | H15: Année 3 : | I15: =I2 -> 1 | J15: =J14+I15 -> 3 | K15: =(J15+(K14-1)*2)+1 -> 12
C16: 0 | D16: 0 | E16: 0 | H16: Année 4 : | I16: =I2 -> 1 | J16: =J15+I16 -> 4 | K16: =(J16+(K15-1)*2)+1 -> 27
C17: 0 | D17: 0 | E17: 0 | H17: Année 5 : | I17: =I2 -> 1 | J17: =J16+I17 -> 5 | K17: =(J17+(K16-1)*2)+1 -> 58
C18: 0 | D18: 0 | E18: 0
C19: 0 | D19: 0 | E19: 0 | H19: Projections financières :
C20: 0 | D20: 0 | E20: 0 | H20: 2 000€ brut/an par filleul€ en direct
C21: 0 | D21: 0 | E21: 0 | H21: 1 000€ brut/an par autre membre de l'équipe
C22: 0 | D22: 0 | E22: 0 | H22: (Données volontairement approximatives)
C23: 0 | D23: 0 | E23: 0
C24: 0 | D24: 0 | E24: 0
C25: 0 | D25: 0 | E25: 0
C26: 0 | D26: 0 | E26: 0
C27: 0 | D27: 0 | E27: 0
C28: 0 | D28: 0 | E28: 0
C29: =SUM(C6:C28) -> 0 | D29: =AVERAGE(D6:D28) -> 0 | E29: =SUM(E6:E28) -> 0

Sheet SuiviFilleuls
A1: Totaux | C1: =COUNTIF(C3:C1048576,"Oui") -> 0 | E1: =COUNTIF(E3:E1048576,"Oui") -> 0 | G1: =COUNTIF(G3:G1048576,"Oui") -> 0 | I1: =COUNTIF(I3:I1048576,"Oui") -> 0 | K1: =COUNTIF(K3:K1048576,"Oui") -> 0
A2: Nom | B2: Prénom | C2: Convention signée | D2: Date signature convention | E2: Habilitation IOBSP | F2: Date examen IOBSP | G2: Habilitation MIA | H2: Date examen MIA | I2: Habilitation ALPSI | J2: Date examen ALPSI | K2: Habilitation CIF | L2: Date examen CIF | M2: Statut

Sheet Plan de carrière
A1: Nom / Prénom : | C1: Projections indicatives!
A2: Date :
A3: Plan de développement et de rémunération à 5 ans
A4: Année PMR | B4: 2026 | C4: 2027 | D4: 2028 | E4: 2029 | F4: 2030
A5: Équipe active | B5: =Développement!K13 -> 2 | C5: =Développement!K14 -> 5 | D5: =Développement!K15 -> 12 | E5: =Développement!K16 -> 27 | F5: =Développement!K17 -> 58
A6: Titre | C6: Senior | D6: Senior | E6: Major | F6: Expert | H6: Cases à remplir manuellement
A7: Qualification | C7: Manager | D7: Planète | E7: Etoile | F7: Galaxie
A8: TPC | B8: 0.05 | C8: 0.06 | D8: 0.065 | E8: 0.07 | F8: 0.08 | H8: TPC à remplir manuellement
A9: VA 4 niveaux (dont perso) | B9: =((B5-1)*125000)+B10 -> 714500 | C9: =((C5-1)*125000)+C10 -> 1200000 | D9: =((D5-1)*125000)+D10 -> 2225000 | E9: =((E5-1)*125000)+E10 -> 4350000 | F9: =((F5-1)*125000)+F10 -> 8675000 | H9: /!\ (VA moyen : 125000€ par membre de l'équipe)
A10: Va perso | B10: =RoadMap2026!F11 -> 589500 | C10: 700000 | D10: 850000 | E10: 1100000 | F10: 1550000 | H10: Cases à remplir manuellement | K10: reporter manuellement depuis l'onglet Production.
A11: Encours AV | B11: =B10*0.35 -> 206325 | C11: =(C10*0.35)+B11 -> 451325 | D11: =(D10*0.35)+C11 -> 748825 | E11: =(E10*0.35)+D11 -> 1133825 | F11: =(F10*0.35)+E11 -> 1676325 | H11: /!\ calcul arbitraire avec 35% du VA de l'année fait en AV. L'encours des années précédentes s'ajoute automatiquement.
A12: VP | B12: =RoadMap2026!E11 -> 1000 | C12: 6400 | D12: 10000 | E12: 13000 | F12: 16000 | H12: Cases à remplir manuellement
H13: * Montant des VP à reporter manuellement depuis la feuille Production (calcul de 100€ moyen par nouveau client). Additionner manuellement les VP d'une année sur l'autre.
A14: Rémunération brute perso | B14: =(B10*B8*0.5) -> 14737.5 | C14: =(C10*C8*0.5) -> 21000 | D14: =(D10*D8*0.5) -> 27625 | E14: =(E10*E8*0.5) -> 38500 | F14: =(F10*F8*0.5) -> 62000
A15: Rémunération brute équipe | B15: =(B9-B10)*0.5*1.5% -> 937.5 | C15: =(C9-C10)*0.5*0.75% -> 1875 | D15: =(D9-D10)*0.5*0.75% -> 5156.25 | E15: =(E9-E10)*0.5*0.75% -> 12187.5 | F15: =(F9-F10)*0.5*0.75% -> 26718.75 | H15: Cases avec formules à ajuster
A16: com récurrence | B16: 0 | C16: =B11*0.35% -> 722.1375 | D16: =C11*0.4% -> 1805.3 | E16: =D11*0.5% -> 3744.125 | F16: =E11*0.55% -> 6236.0375 | H16: Récurrence : | I16: Ajuster le taux en fonction du VA total géré et de la répartition de l'encours (la récurrence est calculée sur l'encours de l'année précédente)
A17: com VP annualisée | B17: =B12*B8*0.4*6 -> 120 | C17: =(B12*C8*0.4)*12+((C12-B12)*C8*0.4*6) -> 1065.6 | D17: =(C12*D8*0.4)*12+((D12-C12)*D8*0.4*6) -> 2558.4 | E17: =(D12*E8*0.4)*12+((E12-D12)*E8*0.4*6) -> 3864 | F17: =(E12*F8*0.4)*12+((F12-E12)*F8*0.4*6) -> 5568
A18: Prime de dèv | B18: 0 | C18: 0 | D18: 0 | E18: =E9*0.35% -> 15225 | F18: =F9*0.4% -> 34700 | H18: Cases à remplir manuellement | K18: (voir calcul avec Manager habilité)
A19: Rémunération brute totale | B19: =SUM(B14:B18) -> 15795 | C19: =SUM(C14:C18) -> 24662.737 | D19: =SUM(D14:D18) -> 37144.95 | E19: =SUM(E14:E18) -> 73520.625 | F19: =SUM(F14:F18) -> 135222.79
A20: rem brute mensu | B20: =B19/12 -> 1316.25 | C20: =C19/12 -> 2055.2281 | D20: =D19/12 -> 3095.4125 | E20: =E19/12 -> 6126.7188 | F20: =F19/12 -> 11268.566
A21: Commission de récurrence sur encours

Sheet Plan d'action
A1: Année PMR : 2023-2024 | C1: Habilitation | D1: R0/R1 | E1: Clients | F1: Filleul | G1: Commissions
A2: 45064 | B2: 45138 | C2: Immo (31/08/2023) | D2: 10 | E2: 5 | F2: 0 | G2: =E2*20000*0.5*3% -> 1500
A3: 45139 | B3: 45291 | C3: MIA + Défi Pro | D3: 15 | E3: 12 | F3: 1 | G3: =E3*0.5*20000*5% -> 6000
A4: 45292 | B4: 45657 | C4: Agent lié | D4: 15 | E4: 12 | F4: 1 | G4: 6500
G5: =SUM(G2:G4) -> 14000
A7: Dates clés! | B7: 6-7 Octobre | C7: Convention Nationale | D7: Montpellier
B8: 8-15 Octobre | C8: Défi Pro | D8: Castelsarrasin
B9: 4-5-6 avril | C9: Mind Master | D9: Paris

Sheet ListeChoixNoms
A1: Proximité | B1: Réseau | C1: Intérêt | D1: Relation
A2: Famille | B2: Chaud | C2: Oui | D2: Reprendre contact
A3: Ami | B3: Tiède | C3: Non | D3: En contact
A4: Collègue | B4: Froid | C4: TBC | D4: Contact perdu
A5: Connaissance
A6: Autre

Sheet ListeRoadMap
A1: Catégore | B1: Produit
A2: Immo | B2: De Normandie
A3: Assurance | B3: LLI
A4: Financier | B4: Résidence principale
A5: Dev équipe | B5: Résidence service neuf
B6: Résidence service ancien
B7: Assurance Vie
B8: PER
B9: Contrat de capitalisation
B10: SCPI
B11: FCPI
B12: FPCI
B13: Girardin
